autogenra/__init__.py
autogenra/autogenchat.py
autogenra/autogenflow.py
autogenra/cli.py
autogenra/datamodel.py
autogenra/version.py
autogenra/utils/__init__.py
autogenra/utils/dbutils.py
autogenra/utils/utils.py
autogenra/web/__init__.py
autogenra/web/app.py
autogenra/web/skills/global/fetch_profile.py
autogenra/web/skills/global/find_papers_arxiv.py
autogenra/web/skills/global/generate_images.py
autogenra/web/ui/404.html
autogenra/web/ui/6c05b3ab656a8bfc225a64b3d73a36a92f83c05e-3ce8b0304a7a995ce2b8.js
autogenra/web/ui/6c05b3ab656a8bfc225a64b3d73a36a92f83c05e-3ce8b0304a7a995ce2b8.js.LICENSE.txt
autogenra/web/ui/6c05b3ab656a8bfc225a64b3d73a36a92f83c05e-3ce8b0304a7a995ce2b8.js.map
autogenra/web/ui/app-645e071c15f891d3995c.js
autogenra/web/ui/app-645e071c15f891d3995c.js.LICENSE.txt
autogenra/web/ui/app-645e071c15f891d3995c.js.map
autogenra/web/ui/chunk-map.json
autogenra/web/ui/component---src-pages-404-tsx-ea218d22b93fdd8a7983.js
autogenra/web/ui/component---src-pages-404-tsx-ea218d22b93fdd8a7983.js.map
autogenra/web/ui/component---src-pages-gallery-index-tsx-47ea544ce2e40f417ad4.js
autogenra/web/ui/component---src-pages-gallery-index-tsx-47ea544ce2e40f417ad4.js.map
autogenra/web/ui/component---src-pages-index-tsx-5643b72f5ad8775a1c03.js
autogenra/web/ui/component---src-pages-index-tsx-5643b72f5ad8775a1c03.js.map
autogenra/web/ui/favicon-32x32.png
autogenra/web/ui/framework-67c0608e158f662ae887.js
autogenra/web/ui/framework-67c0608e158f662ae887.js.LICENSE.txt
autogenra/web/ui/framework-67c0608e158f662ae887.js.map
autogenra/web/ui/index.html
autogenra/web/ui/manifest.webmanifest
autogenra/web/ui/styles.53e218fe2aeaefa906e0.css
autogenra/web/ui/webpack-runtime-40780b8656a08f75a346.js
autogenra/web/ui/webpack-runtime-40780b8656a08f75a346.js.map
autogenra/web/ui/webpack.stats.json
autogenra/web/ui/404/index.html
autogenra/web/ui/gallery/index.html
autogenra/web/ui/icons/icon-144x144.png
autogenra/web/ui/icons/icon-192x192.png
autogenra/web/ui/icons/icon-256x256.png
autogenra-0.0.10a0.dist-info/METADATA
autogenra-0.0.10a0.dist-info/WHEEL
autogenra-0.0.10a0.dist-info/entry_points.txt
autogenra-0.0.10a0.dist-info/top_level.txt
autogenra-0.0.10a0.dist-info/RECORD
