Metadata-Version: 2.1
Name: autogenra
Version: 0.0.10a0
Summary: Autogen Assistant UI
Author-email: Autogen Team <autogen@microsoft.com>
Project-URL: Homepage, https://github.com/microsoft/autogen
Project-URL: Bug Tracker, https://github.com/microsoft/autogen/issues
Classifier: Programming Language :: Python :: 3
Classifier: License :: OSI Approved :: MIT License
Classifier: Operating System :: OS Independent
Requires-Python: >=3.9
Requires-Dist: pydantic
Requires-Dist: fastapi
Requires-Dist: typer
Requires-Dist: uvicorn
Requires-Dist: arxiv
Requires-Dist: pyautogen ==0.2.0
Provides-Extra: web
Requires-Dist: fastapi ; extra == 'web'
Requires-Dist: uvicorn ; extra == 'web'
